COPYING.LESSER
python_ags4/AGS4.py
python_ags4/Standard_dictionary_v4_0_3.ags
python_ags4/Standard_dictionary_v4_0_4.ags
python_ags4/Standard_dictionary_v4_1.ags
python_ags4/Standard_dictionary_v4_1_1.ags
python_ags4/__init__.py
python_ags4/ags4_cli.py
python_ags4/check.py
python_ags4/data/__init__.py
python_ags4/data/test_data.ags
python_ags4/utils.py
python_ags4-1.1.0.dist-info/COPYING.LESSER
python_ags4-1.1.0.dist-info/LICENSE
python_ags4-1.1.0.dist-info/METADATA
python_ags4-1.1.0.dist-info/WHEEL
python_ags4-1.1.0.dist-info/entry_points.txt
python_ags4-1.1.0.dist-info/RECORD
