Metadata-Version: 2.1
Name: python-AGS4
Version: 1.1.0
Summary: A library to read, write, and check AGS4 files using Pandas DataFrames
Home-page: https://github.com/asitha-sena/python-AGS4
License: LGPL-3.0
Author: Asitha Senanayake
Author-email: asitha_sena@yahoo.com
Requires-Python: >=3.9,<4.0
Classifier: License :: OSI Approved :: GNU Lesser General Public License v3 (LGPLv3)
Classifier: Programming Language :: Python :: 3
Classifier: Programming Language :: Python :: 3.9
Classifier: Programming Language :: Python :: 3.10
Classifier: Programming Language :: Python :: 3.11
Classifier: Programming Language :: Python :: 3.12
Requires-Dist: click (>=7.0,<9.0)
Requires-Dist: defusedxml (>=0.6,<0.8)
Requires-Dist: openpyxl (>=3.0,<4.0)
Requires-Dist: pandas (>=2.1,<3.0)
Requires-Dist: rich (>=9.0,<14.0)
Project-URL: Repository, https://gitlab.com/ags-data-format-wg/ags-python-library
